Metadata-Version: 2.4
Name: hy3dgen
Version: 2.0.1
Home-page: https://github.com/Tencent/Hunyuan3D-2
License-File: LICENSE
License-File: NOTICE
Requires-Dist: gradio
Requires-Dist: tqdm
Requires-Dist: torch
Requires-Dist: torchvision
Requires-Dist: numpy
Requires-Dist: ninja
Requires-Dist: diffusers
Requires-Dist: pybind11
Requires-Dist: opencv-python
Requires-Dist: einops
Requires-Dist: transformers
Requires-Dist: omegaconf
Requires-Dist: trimesh
Requires-Dist: pymeshlab
Requires-Dist: pygltflib
Requires-Dist: xatlas
Requires-Dist: accelerate
Requires-Dist: gradio
Requires-Dist: fastapi
Requires-Dist: uvicorn
Requires-Dist: rembg
Requires-Dist: onnxruntime
Dynamic: home-page
Dynamic: license-file
Dynamic: requires-dist
